drf_api_auth/__init__.py
drf_api_auth/admin.py
drf_api_auth/apps.py
drf_api_auth/authentications.py
drf_api_auth/models.py
drf_api_auth/settings.py
drf_api_auth/migrations/0001_initial.py
drf_api_auth/migrations/0002_alter_apiauth_id.py
drf_api_auth/migrations/__init__.py
drf_api_auth-0.1.3.dist-info/LICENSE.md
drf_api_auth-0.1.3.dist-info/METADATA
drf_api_auth-0.1.3.dist-info/WHEEL
drf_api_auth-0.1.3.dist-info/top_level.txt
drf_api_auth-0.1.3.dist-info/RECORD
