Metadata-Version: 2.1
Name: drf-api-auth
Version: 0.1.3
Summary: A Django app to authenticate by api_key and api_secret
Home-page: https://github.com/amin-basiri/drf_api_auth
Author: Amin Basiri
Author-email: amin.bsr99@gmail.com
License: BSD-3-Clause
Classifier: Environment :: Web Environment
Classifier: Framework :: Django
Classifier: Framework :: Django :: 4.2
Classifier: License :: OSI Approved :: BSD License
Classifier: Operating System :: OS Independent
Classifier: Programming Language :: Python
Classifier: Programming Language :: Python :: 3.9
Requires-Python: >=3.9
License-File: LICENSE.md
Requires-Dist: Django >=4
Requires-Dist: djangorestframework >=3
